skconfig/__init__.py
skconfig/_version.py
skconfig/config.py
skconfig/tests/2010-10-22_vis_psf.yaml
skconfig/tests/__init__.py
skconfig/tests/test_config.py
skconfig/tests/test_configuration.yaml
skconfig-0.3.7.dist-info/licenses/LICENSE
skconfig-0.3.7.dist-info/METADATA
skconfig-0.3.7.dist-info/WHEEL
skconfig-0.3.7.dist-info/top_level.txt
skconfig-0.3.7.dist-info/RECORD
