Metadata-Version: 2.4
Name: skconfig
Version: 0.3.7
Summary: YAML based configuration, adds an extension to use yaml-based macros and environment variables
Author-email: Nick Lloyd <nick.lloyd@usask.ca>
License: MIT
Classifier: Development Status :: 4 - Beta
Classifier: Programming Language :: Python :: 3 :: Only
Classifier: Programming Language :: Python :: 3.10
Classifier: Programming Language :: Python :: 3.11
Classifier: Programming Language :: Python :: 3.12
Requires-Python: >=3.6
License-File: LICENSE
Requires-Dist: numpy
Requires-Dist: PyYAML>6.0.0
Requires-Dist: appdirs
Requires-Dist: packaging
Provides-Extra: test
Requires-Dist: pytest; extra == "test"
Dynamic: license-file
